injection_manager/__init__.py
injection_manager/managers/EventInjectionManager.py
injection_manager/managers/InjectionManager.py
injection_manager/managers/__init__.py
injection_manager/typeclass/Injectable.py
injection_manager/typeclass/Session.py
injection_manager/typeclass/__init__.py
injection_manager-0.1.3.dist-info/METADATA
injection_manager-0.1.3.dist-info/WHEEL
injection_manager-0.1.3.dist-info/top_level.txt
injection_manager-0.1.3.dist-info/RECORD
