Metadata-Version: 2.2
Name: injection-manager
Version: 0.1.3
Summary: An async-enabled injection framework for StarCraft data.
Home-page: https://github.com/OpenJ92/injection-manager
Author: Jacob Vartuli-Schonberg
Author-email: jacob.vartuli.schonberg@gmail.com
Classifier: Programming Language :: Python :: 3
Classifier: License :: OSI Approved :: MIT License
Classifier: Operating System :: OS Independent
Requires-Python: >=3.8
Dynamic: author
Dynamic: author-email
Dynamic: classifier
Dynamic: home-page
Dynamic: requires-python
Dynamic: summary
